{"shentong":{"name":"申通快递","short_name":"申通","code":"shentong","url":null},"ems":{"name":"EMS","short_name":"EMS","code":"ems","url":null},"shunfeng":{"name":"顺丰速运","short_name":"顺丰","code":"shunfeng","url":null},"yunda":{"name":"韵达快运","short_name":"韵达","code":"yunda","url":null},"yuantong":{"name":"圆通速递","short_name":"圆通","code":"yuantong","url":null},"zhongtong":{"name":"中通速递","short_name":"中通","code":"zhongtong","url":null},"huitongkuaidi":{"name":"百世汇通","short_name":"汇通","code":"huitongkuaidi","url":null},"tiantian":{"name":"天天快递","short_name":"天天","code":"tiantian","url":null},"zhaijisong":{"name":"宅急送","short_name":"宅急送","code":"zhaijisong","url":null},"xinhongyukuaidi":{"name":"鑫飞鸿","short_name":"鑫飞鸿","code":"xinhongyukuaidi","url":null},"cces":{"name":"CCES(国通快递)","short_name":"CCES","code":"cces","url":null},"quanyikuaidi":{"name":"全一快递","short_name":"全一","code":"quanyikuaidi","url":null},"biaojikuaidi":{"name":"彪记快递","short_name":"彪记","code":"biaojikuaidi","url":null},"xingchengjibian":{"name":"星晨急便","short_name":"星晨急便","code":"xingchengjibian","url":null},"yafengsudi":{"name":"亚风速递","short_name":"亚风","code":"yafengsudi","url":null},"yuanweifeng":{"name":"源伟丰","short_name":"源伟丰","code":"yuanweifeng","url":null},"quanritongkuaidi":{"name":"全日通","short_name":"全日通","code":"quanritongkuaidi","url":null},"anxindakuaixi":{"name":"安信达","short_name":"安信达","code":"anxindakuaixi","url":null},"minghangkuaidi":{"name":"民航快递","short_name":"民航","code":"minghangkuaidi","url":null},"fenghuangkuaidi":{"name":"凤凰快递","short_name":"凤凰","code":"fenghuangkuaidi","url":null},"jinguangsudikuaijian":{"name":"京广速递","short_name":"京广","code":"jinguangsudikuaijian","url":null},"peisihuoyunkuaidi":{"name":"配思货运","short_name":"配思","code":"peisihuoyunkuaidi","url":null},"ztky":{"name":"中铁物流","short_name":"中铁","code":"ztky","url":null},"ups":{"name":"UPS","short_name":"UPS","code":"ups","url":null},"fedex":{"name":"FedEx-国际件","short_name":"FedEx","code":"fedex","url":null},"tnt":{"name":"TNT","short_name":"TNT","code":"tnt","url":null},"dhl":{"name":"DHL-中国件","short_name":"DHL","code":"dhl","url":null},"aae":{"name":"AAE-中国件","short_name":"AAE","code":"aae","url":null},"datianwuliu":{"name":"大田物流","short_name":"大田","code":"datianwuliu","url":null},"debangwuliu":{"name":"德邦物流","short_name":"德邦","code":"debangwuliu","url":null},"xinbangwuliu":{"name":"新邦物流","short_name":"新邦","code":"xinbangwuliu","url":null},"longbanwuliu":{"name":"龙邦速递","short_name":"龙邦","code":"longbanwuliu","url":null},"yibangwuliu":{"name":"一邦速递","short_name":"一邦","code":"yibangwuliu","url":null},"suer":{"name":"速尔快递","short_name":"速尔","code":"suer","url":null},"lianhaowuliu":{"name":"联昊通","short_name":"联昊通","code":"lianhaowuliu","url":null},"guangdongyouzhengwuliu":{"name":"广东邮政","short_name":"广东邮政","code":"guangdongyouzhengwuliu","url":null},"zhongyouwuliu":{"name":"中邮物流","short_name":"中邮","code":"zhongyouwuliu","url":null},"tiandihuayu":{"name":"天地华宇","short_name":"华宇","code":"tiandihuayu","url":null},"shenghuiwuliu":{"name":"盛辉物流","short_name":"盛辉","code":"shenghuiwuliu","url":null},"changyuwuliu":{"name":"长宇物流","short_name":"长宇","code":"changyuwuliu","url":null},"feikangda":{"name":"飞康达","short_name":"飞康达","code":"feikangda","url":null},"yuanzhijiecheng":{"name":"元智捷诚","short_name":"元智捷诚","code":"yuanzhijiecheng","url":null},"youzhengguonei":{"name":"包裹/平邮","short_name":"邮政国内","code":"youzhengguonei","url":null},"youzhengguoji":{"name":"国际包裹","short_name":"邮政国际","code":"youzhengguoji","url":null},"wanjiawuliu":{"name":"万家物流","short_name":"万家","code":"wanjiawuliu","url":null},"yuanchengwuliu":{"name":"远成物流","short_name":"远成","code":"yuanchengwuliu","url":null},"xinfengwuliu":{"name":"信丰物流","short_name":"信丰","code":"xinfengwuliu","url":null},"wenjiesudi":{"name":"文捷航空","short_name":"文捷","code":"wenjiesudi","url":null},"quanchenkuaidi":{"name":"全晨快递","short_name":"全晨","code":"quanchenkuaidi","url":null},"jiayiwuliu":{"name":"佳怡物流","short_name":"佳怡","code":"jiayiwuliu","url":null},"youshuwuliu":{"name":"优速快递","short_name":"优速","code":"youshuwuliu","url":null},"kuaijiesudi":{"name":"快捷速递","short_name":"快捷","code":"kuaijiesudi","url":null},"dsukuaidi":{"name":"D速快递","short_name":"D速","code":"dsukuaidi","url":null},"quanjitong":{"name":"全际通","short_name":"全际通","code":"quanjitong","url":null},"ganzhongnengda":{"name":"能达速递","short_name":"能达","code":"ganzhongnengda","url":null},"anjiekuaidi":{"name":"青岛安捷快递","short_name":"安捷","code":"anjiekuaidi","url":null},"yuefengwuliu":{"name":"越丰物流","short_name":"越丰","code":"yuefengwuliu","url":null},"dpex":{"name":"DPEX","short_name":"DPEX","code":"dpex","url":null},"jixianda":{"name":"急先达","short_name":"急先达","code":"jixianda","url":null},"baifudongfang":{"name":"百福东方","short_name":"百福东方","code":"baifudongfang","url":null},"bht":{"name":"BHT","short_name":"BHT","code":"bht","url":null},"wuyuansudi":{"name":"伍圆速递","short_name":"伍圆","code":"wuyuansudi","url":null},"lanbiaokuaidi":{"name":"蓝镖快递","short_name":"蓝镖","code":"lanbiaokuaidi","url":null},"coe":{"name":"COE","short_name":"COE","code":"coe","url":null},"nanjing":{"name":"南京100","short_name":"南京100","code":"nanjing","url":null},"hengluwuliu":{"name":"恒路物流","short_name":"恒路","code":"hengluwuliu","url":null},"jindawuliu":{"name":"金大物流","short_name":"金大","code":"jindawuliu","url":null},"huaxialongwuliu":{"name":"华夏龙","short_name":"华夏龙","code":"huaxialongwuliu","url":null},"yuntongkuaidi":{"name":"运通快递","short_name":"运通","code":"yuntongkuaidi","url":null},"jiajiwuliu":{"name":"佳吉快运","short_name":"佳吉","code":"jiajiwuliu","url":null},"shengfengwuliu":{"name":"盛丰物流","short_name":"盛丰","code":"shengfengwuliu","url":null},"yuananda":{"name":"源安达","short_name":"源安达","code":"yuananda","url":null},"jiayunmeiwuliu":{"name":"加运美","short_name":"加运美","code":"jiayunmeiwuliu","url":null},"wanxiangwuliu":{"name":"万象物流","short_name":"万象","code":"wanxiangwuliu","url":null},"hongpinwuliu":{"name":"宏品物流","short_name":"宏品","code":"hongpinwuliu","url":null},"gls":{"name":"GLS","short_name":"GLS","code":"gls","url":null},"shangda":{"name":"上大物流","short_name":"上大","code":"shangda","url":null},"zhongtiewuliu":{"name":"中铁快运","short_name":"中铁","code":"zhongtiewuliu","url":null},"yuanfeihangwuliu":{"name":"原飞航","short_name":"原飞航","code":"yuanfeihangwuliu","url":null},"haiwaihuanqiu":{"name":"海外环球","short_name":"海外环球","code":"haiwaihuanqiu","url":null},"santaisudi":{"name":"三态速递","short_name":"三态","code":"santaisudi","url":null},"jinyuekuaidi":{"name":"晋越快递","short_name":"晋越","code":"jinyuekuaidi","url":null},"lianbangkuaidi":{"name":"联邦快递","short_name":"联邦","code":"lianbangkuaidi","url":null},"feikuaida":{"name":"飞快达","short_name":"飞快达","code":"feikuaida","url":null},"quanfengkuaidi":{"name":"全峰快递","short_name":"全峰","code":"quanfengkuaidi","url":null},"rufengda":{"name":"如风达","short_name":"如风达","code":"rufengda","url":null},"lejiedi":{"name":"乐捷递","short_name":"乐捷递","code":"lejiedi","url":null},"zhongxinda":{"name":"忠信达","short_name":"忠信达","code":"zhongxinda","url":null},"zhimakaimen":{"name":"芝麻开门","short_name":"芝麻开门","code":"zhimakaimen","url":null},"saiaodi":{"name":"赛澳递","short_name":"赛澳递","code":"saiaodi","url":null},"haihongwangsong":{"name":"海红网送","short_name":"海红网送","code":"haihongwangsong","url":null},"gongsuda":{"name":"共速达","short_name":"共速达","code":"gongsuda","url":null},"jialidatong":{"name":"嘉里大通","short_name":"嘉里大通","code":"jialidatong","url":null},"ocs":{"name":"OCS","short_name":"OCS","code":"ocs","url":null},"usps":{"name":"USPS","short_name":"USPS","code":"usps","url":null},"meiguokuaidi":{"name":"美国快递","short_name":"美国","code":"meiguokuaidi","url":null},"lijisong":{"name":"立即送","short_name":"立即送","code":"lijisong","url":null},"yinjiesudi":{"name":"银捷速递","short_name":"银捷","code":"yinjiesudi","url":null},"menduimen":{"name":"门对门","short_name":"门对门","code":"menduimen","url":null},"disifang":{"name":"递四方","short_name":"递四方","code":"disifang","url":null},"zhengzhoujianhua":{"name":"郑州建华","short_name":"郑州建华","code":"zhengzhoujianhua","url":null},"hebeijianhua":{"name":"河北建华","short_name":"河北建华","code":"hebeijianhua","url":null},"weitepai":{"name":"微特派","short_name":"微特派","code":"weitepai","url":null},"dhlde":{"name":"DHL-德国件","short_name":"DHL-德国件","code":"dhlde","url":null},"tonghetianxia":{"name":"通和天下","short_name":"通和天下","code":"tonghetianxia","url":null},"emsguoji":{"name":"EMS-国际件","short_name":"EMS-国际件","code":"emsguoji","url":null},"fedexus":{"name":"FedEx-美国件","short_name":"FedEx","code":"fedexus","url":null},"fengxingtianxia":{"name":"风行天下","short_name":"风行天下","code":"fengxingtianxia","url":null},"kangliwuliu":{"name":"康力物流","short_name":"康力","code":"kangliwuliu","url":null},"kuayue":{"name":"跨越速递","short_name":"跨越","code":"kuayue","url":null},"haimengsudi":{"name":"海盟速递","short_name":"海盟","code":"haimengsudi","url":null},"shenganwuliu":{"name":"圣安物流","short_name":"圣安","code":"shenganwuliu","url":null},"yitongfeihong":{"name":"一统飞鸿","short_name":"一统飞鸿","code":"yitongfeihong","url":null},"zhongsukuaidi":{"name":"中速快件","short_name":"中速","code":"zhongsukuaidi","url":null},"neweggozzo":{"name":"新蛋奥硕","short_name":"新蛋奥硕","code":"neweggozzo","url":null},"ontrac":{"name":"OnTrac","short_name":"OnTrac","code":"ontrac","url":null},"sevendays":{"name":"七天连锁","short_name":"七天连锁","code":"sevendays","url":null},"mingliangwuliu":{"name":"明亮物流","short_name":"明亮","code":"mingliangwuliu","url":null},"vancl":{"name":"凡客配送","short_name":"凡客","code":"vancl","url":null},"emsen":{"name":"EMS英文","short_name":"华企","code":"emsen","url":null},"huaqikuaiyun":{"name":"华企快运","short_name":"城市100","code":"huaqikuaiyun","url":null},"city100":{"name":"城市100","short_name":"红马甲","code":"city100","url":null},"sxhongmajia":{"name":"红马甲物流","short_name":"穗佳","code":"sxhongmajia","url":null},"suijiawuliu":{"name":"穗佳物流","short_name":"飞豹","code":"suijiawuliu","url":null},"feibaokuaidi":{"name":"飞豹快递","short_name":"传喜","code":"feibaokuaidi","url":null},"chuanxiwuliu":{"name":"传喜物流","short_name":"捷特","code":"chuanxiwuliu","url":null},"jietekuaidi":{"name":"捷特快递","short_name":"隆浪","code":"jietekuaidi","url":null},"longlangkuaidi":{"name":"隆浪快递","short_name":"EMS-英文","code":"longlangkuaidi","url":null},"zhongtianwanyun":{"name":"中天万运","short_name":"中天万运","code":"zhongtianwanyun","url":null},"hkpost":{"name":"香港邮政","short_name":"香港邮政","code":"hkpost","url":null},"bangsongwuliu":{"name":"邦送物流","short_name":"邦送","code":"bangsongwuliu","url":null},"guotongkuaidi":{"name":"国通快递","short_name":"国通","code":"guotongkuaidi","url":null},"auspost":{"name":"澳大利亚邮政","short_name":"澳州邮政","code":"auspost","url":null},"canpost":{"name":"加拿大邮政-英文版","short_name":"加拿大邮政-英文版","code":"canpost","url":null},"canpostfr":{"name":"加拿大邮政-法文版","short_name":"加拿大邮政-法文版","code":"canpostfr","url":null},"upsen":{"name":"UPS-全球件","short_name":"UPS-全球件","code":"upsen","url":null},"tnten":{"name":"TNT-全球件","short_name":"TNT-全球件","code":"tnten","url":null},"dhlen":{"name":"DHL-全球件","short_name":"DHL-全球件","code":"dhlen","url":null},"shunfengen":{"name":"顺丰-美国件","short_name":"顺丰-美国件","code":"shunfengen","url":null},"huiqiangkuaidi":{"name":"汇强快递","short_name":"汇强","code":"huiqiangkuaidi","url":null},"xiyoutekuaidi":{"name":"希优特","short_name":"希优特","code":"xiyoutekuaidi","url":null},"haoshengwuliu":{"name":"昊盛物流","short_name":"昊盛","code":"haoshengwuliu","url":null},"shangcheng":{"name":"尚橙物流","short_name":"尚橙","code":"shangcheng","url":null},"yilingsuyun":{"name":"亿领速运","short_name":"亿领","code":"yilingsuyun","url":null},"dayangwuliu":{"name":"大洋物流","short_name":"大洋","code":"dayangwuliu","url":null},"didasuyun":{"name":"递达速运","short_name":"递达","code":"didasuyun","url":null},"yitongda":{"name":"易通达","short_name":"易通达","code":"yitongda","url":null},"youbijia":{"name":"邮必佳","short_name":"邮必佳","code":"youbijia","url":null},"yishunhang":{"name":"亿顺航","short_name":"亿顺航","code":"yishunhang","url":null},"feihukuaidi":{"name":"飞狐快递","short_name":"飞狐","code":"feihukuaidi","url":null},"xiaoxiangchenbao":{"name":"潇湘晨报","short_name":"潇湘晨报","code":"xiaoxiangchenbao","url":null},"balunzhi":{"name":"巴伦支","short_name":"巴伦支","code":"balunzhi","url":null},"aramex":{"name":"Aramex","short_name":"Aramex","code":"aramex","url":null},"minshengkuaidi":{"name":"闽盛快递","short_name":"闽盛","code":"minshengkuaidi","url":null},"syjiahuier":{"name":"佳惠尔","short_name":"佳惠尔","code":"syjiahuier","url":null},"minbangsudi":{"name":"民邦速递","short_name":"民邦","code":"minbangsudi","url":null},"shanghaikuaitong":{"name":"上海快通","short_name":"上海快通","code":"shanghaikuaitong","url":null},"xiaohongmao":{"name":"北青小红帽","short_name":"北青小红帽","code":"xiaohongmao","url":null},"gsm":{"name":"GSM","short_name":"GSM","code":"gsm","url":null},"annengwuliu":{"name":"安能物流","short_name":"安能","code":"annengwuliu","url":null},"kcs":{"name":"KCS","short_name":"KCS","code":"kcs","url":null},"citylink":{"name":"City-Link","short_name":"City-Link","code":"citylink","url":null},"diantongkuaidi":{"name":"店通快递","short_name":"店通","code":"diantongkuaidi","url":null},"fanyukuaidi":{"name":"凡宇快递","short_name":"凡宇","code":"fanyukuaidi","url":null},"pingandatengfei":{"name":"平安达腾飞","short_name":"平安达腾飞","code":"pingandatengfei","url":null},"jiajikuaidi":{"name":"佳吉快递","short_name":"广东通路","code":"jiajikuaidi","url":null},"guangdongtonglu":{"name":"广东通路","short_name":"中睿","code":"guangdongtonglu","url":null},"zhongruisudi":{"name":"中睿速递","short_name":"快达","code":"zhongruisudi","url":null},"kuaidawuliu":{"name":"快达物流","short_name":"佳吉","code":"kuaidawuliu","url":null},"adp":{"name":"ADP国际快递","short_name":"ADP","code":"adp","url":null},"fardarww":{"name":"颿达国际快递","short_name":"颿达","code":"fardarww","url":null},"fandaguoji":{"name":"颿达国际快递(英文)","short_name":"颿达国际","code":"fandaguoji","url":null},"shlindao":{"name":"林道国际快递","short_name":"林道","code":"shlindao","url":null},"sinoex":{"name":"中外运速递(英文)","short_name":"中外运","code":"sinoex","url":null},"zhongwaiyun":{"name":"中外运速递","short_name":"中外运速递","code":"zhongwaiyun","url":null},"dechuangwuliu":{"name":"深圳德创物流","short_name":"深圳德创","code":"dechuangwuliu","url":null},"ldxpres":{"name":"林道国际快递(英文)","short_name":"林道国际快递(英文)","code":"ldxpres","url":null},"ruidianyouzheng":{"name":"瑞典邮政包裹小包","short_name":"瑞典邮政包裹小包","code":"ruidianyouzheng","url":null},"postenab":{"name":"Posten AB","short_name":"Posten AB","code":"postenab","url":null},"nuoyaao":{"name":"偌亚奥国际快递","short_name":"偌亚奥","code":"nuoyaao","url":null},"chengjisudi":{"name":"城际速递","short_name":"城际","code":"chengjisudi","url":null},"xianglongyuntong":{"name":"祥龙运通物流","short_name":"祥龙运通","code":"xianglongyuntong","url":null},"pinsuxinda":{"name":"品速心达快递","short_name":"品速心达","code":"pinsuxinda","url":null},"yuxinwuliu":{"name":"宇鑫物流","short_name":"宇鑫","code":"yuxinwuliu","url":null},"peixingwuliu":{"name":"陪行物流","short_name":"陪行物流","code":"peixingwuliu","url":null},"hutongwuliu":{"name":"户通物流","short_name":"户通物流","code":"hutongwuliu","url":null},"xianchengliansudi":{"name":"西安城联速递","short_name":"西安城联速递","code":"xianchengliansudi","url":null},"yujiawuliu":{"name":"煜嘉物流","short_name":"煜嘉物流","code":"yujiawuliu","url":null},"yiqiguojiwuliu":{"name":"一柒国际物流","short_name":"一柒国际物流","code":"yiqiguojiwuliu","url":null},"fedexcn":{"name":"Fedex中文","short_name":"FedEx","code":"fedexcn","url":null},"lianbangkuaidien":{"name":"联邦快递英文","short_name":"联邦快递英文","code":"lianbangkuaidien","url":null},"zhongtongphone":{"name":"中通（带电话）","short_name":"中通（带电话）","code":"zhongtongphone","url":null},"saiaodimmb":{"name":"赛澳递for买卖宝","short_name":"赛澳递for买卖宝","code":"saiaodimmb","url":null},"shanghaiwujiangmmb":{"name":"上海无疆for买卖宝","short_name":"上海无疆for买卖宝","code":"shanghaiwujiangmmb","url":null},"singpost":{"name":"新加坡邮政","short_name":"新加坡邮政","code":"singpost","url":null},"bpost":{"name":"比利时邮政","short_name":"比利时邮政","code":"bpost","url":null},"yinsu":{"name":"音素快运","short_name":"音素快运","code":"yinsu","url":null},"ndwl":{"name":"南方传媒物流","short_name":"南方传媒物流","code":"ndwl","url":null},"sucheng":{"name":"速呈宅配","short_name":"速呈宅配","code":"sucheng","url":null},"chuangyi":{"name":"创一快递","short_name":"创一快递","code":"chuangyi","url":null},"dianyi":{"name":"云南滇驿物流","short_name":"云南滇驿物流","code":"dianyi","url":null},"cqxingcheng":{"name":"重庆星程快递","short_name":"重庆星程快递","code":"cqxingcheng","url":null},"scxingcheng":{"name":"四川星程快递","short_name":"四川星程快递","code":"scxingcheng","url":null},"gzxingcheng":{"name":"贵州星程快递","short_name":"贵州星程快递","code":"gzxingcheng","url":null},"ytkd":{"name":"运通中港快递","short_name":"运通中港快递","code":"ytkd","url":null},"gatien":{"name":"gati官网英文通道","short_name":"gati官网英文通道","code":"gatien","url":null},"gaticn":{"name":"gati官网中文通道","short_name":"gati官网中文通道","code":"gaticn","url":null},"jcex":{"name":"jcex官网通道","short_name":"jcex官网通道","code":"jcex","url":null},"peex":{"name":"派尔快递官网通道","short_name":"派尔快递官网通道","code":"peex","url":null},"kxda":{"name":"凯信达官网通道","short_name":"凯信达官网通道","code":"kxda","url":null},"advancing":{"name":"安达信官网通道","short_name":"安达信官网通道","code":"advancing","url":null},"huiwen":{"name":"汇文官网通道","short_name":"汇文官网通道","code":"huiwen","url":null},"yxexpress":{"name":"亿翔官网通道","short_name":"亿翔官网通道","code":"yxexpress","url":null},"donghong":{"name":"东红合作通道","short_name":"东红合作通道","code":"donghong","url":null},"feiyuanvipshop":{"name":"飞远配送","short_name":"飞远配送","code":"feiyuanvipshop","url":null},"szems":{"name":"深圳EMS","short_name":"深圳EMS","code":"szems","url":null},"hlyex":{"name":"好运来","short_name":"好运来","code":"hlyex","url":null},"dpexen":{"name":"dpex国际","short_name":"dpex国际","code":"dpexen","url":null},"zengyisudi":{"name":"增益速递","short_name":"增益速递","code":"zengyisudi","url":null},"kuaiyouda":{"name":"四川快优达速递","short_name":"四川快优达速递","code":"kuaiyouda","url":null},"riyuwuliu":{"name":"日昱物流","short_name":"日昱物流","code":"riyuwuliu","url":null},"sutongwuliu":{"name":"速通物流","short_name":"速通物流","code":"sutongwuliu","url":null},"nanjingshengbang":{"name":"南京晟邦物流","short_name":"南京晟邦物流","code":"nanjingshengbang","url":null}}